altf1be_json_helpers/__init__.py
altf1be_json_helpers/altf1be_json_helpers.py
altf1be_json_helpers/altf1be_json_helpers_unittest.py
altf1be_json_helpers-1.0.4.dist-info/LICENSE
altf1be_json_helpers-1.0.4.dist-info/METADATA
altf1be_json_helpers-1.0.4.dist-info/WHEEL
altf1be_json_helpers-1.0.4.dist-info/top_level.txt
altf1be_json_helpers-1.0.4.dist-info/RECORD
