Metadata-Version: 2.1
Name: altf1be-json-helpers
Version: 1.0.4
Summary: Helpers to deal with basic requirements of the management of a JSON File. A library built by www.alt-f1.be
Home-page: https://github.com/ALT-F1/altf1be_json_helpers
Author: Abdelkrim Boujraf
Author-email: abo+altf1be_json_helpers_pkg@alt-f1.be
License: LICENSE
Project-URL: Bug Reports, https://github.com/ALT-F1/altf1be_json_helpers/issues/new
Project-URL: Company behind the library, http://www.alt-f1.be
Project-URL: Source, https://github.com/ALT-F1/altf1be_json_helpers
Keywords: library,altf1be_json_helpers,alt-f1.be,helpers-library,python3,pypi-package
Platform: UNKNOWN
Classifier: Development Status :: 5 - Production/Stable
Classifier: Intended Audience :: Developers
Classifier: License :: OSI Approved :: European Union Public Licence 1.2 (EUPL 1.2)
Classifier: Operating System :: OS Independent
Classifier: Programming Language :: Python :: 3.7
Classifier: Topic :: Software Development :: Libraries :: Python Modules
Requires-Python: >=3.5
Requires-Dist: altf1be-helpers (==1.0.2)
